Metadata-Version: 1.1
Name: projects
Version: 1.0.6
Summary: The intuitive project manager
Home-page: https://github.com/tiborsimon/projects
Author: Tibor Simon
Author-email: tibor@tiborsimon.io
License: MIT
Keywords: project management command line terminal projects tool utility script scripting engine manual man
Platform: UNKNOWN
Classifier: Development Status :: 2 - Pre-Alpha
Classifier: Intended Audience :: Developers
Classifier: Topic :: Utilities
Classifier: Environment :: Console
Classifier: Natural Language :: English
Classifier: Operating System :: MacOS :: MacOS X
Classifier: Operating System :: Unix
Classifier: License :: OSI Approved :: MIT License
Classifier: Programming Language :: Python
